galaxykit/__init__.py
galaxykit/_version.py
galaxykit/client.py
galaxykit/collections.py
galaxykit/command.py
galaxykit/constants.py
galaxykit/container_images.py
galaxykit/containers.py
galaxykit/containerutils.py
galaxykit/distributions.py
galaxykit/greet.py
galaxykit/groups.py
galaxykit/namespaces.py
galaxykit/registries.py
galaxykit/remotes.py
galaxykit/repositories.py
galaxykit/roles.py
galaxykit/tasks.py
galaxykit/users.py
galaxykit/utils.py
galaxykit-0.14.0.dist-info/LICENSE.md
galaxykit-0.14.0.dist-info/METADATA
galaxykit-0.14.0.dist-info/WHEEL
galaxykit-0.14.0.dist-info/entry_points.txt
galaxykit-0.14.0.dist-info/top_level.txt
galaxykit-0.14.0.dist-info/RECORD
