Metadata-Version: 2.1
Name: galaxykit
Version: 0.14.0
Summary: A small client library for testing galaxy_ng.
Home-page: https://github.com/hendersonreed/galaxykit/
Author: Red Hat PEAQE Team
License: GPLv2
License-File: LICENSE.md
Requires-Dist: requests
Requires-Dist: simplejson
Requires-Dist: orionutils
Requires-Dist: pyyaml
